hiphive/__init__.py
hiphive/cluster_space.py
hiphive/cluster_space_data.py
hiphive/config.py
hiphive/cutoffs.py
hiphive/force_constant_model.py
hiphive/force_constant_potential.py
hiphive/force_constants.py
hiphive/structure_container.py
hiphive/utilities.py
hiphive/calculators/__init__.py
hiphive/calculators/ase_calculator.py
hiphive/calculators/numba_calc.py
hiphive/calculators/zbl.py
hiphive/core/__init__.py
hiphive/core/atoms.py
hiphive/core/cluster_space_builder.py
hiphive/core/clusters.py
hiphive/core/config.py
hiphive/core/debug.py
hiphive/core/eigentensors.py
hiphive/core/orbits.py
hiphive/core/rotational_constraints.py
hiphive/core/structure_alignment.py
hiphive/core/structures.py
hiphive/core/tensors.py
hiphive/core/translational_constraints.py
hiphive/core/utilities.py
hiphive/input_output/__init__.py
hiphive/input_output/gpumd.py
hiphive/input_output/logging_tools.py
hiphive/input_output/phonopy.py
hiphive/input_output/pretty_table_prints.py
hiphive/input_output/read_write_files.py
hiphive/input_output/shengBTE.py
hiphive/md_tools/__init__.py
hiphive/md_tools/spectral_energy_density.py
hiphive/self_consistent_phonons/__init__.py
hiphive/self_consistent_phonons/self_consistent_harmonic_model.py
hiphive/structure_generation/__init__.py
hiphive/structure_generation/phonon.py
hiphive/structure_generation/rattle.py
hiphive-1.5.dist-info/licenses/LICENSE
hiphive-1.5.dist-info/METADATA
hiphive-1.5.dist-info/WHEEL
hiphive-1.5.dist-info/top_level.txt
hiphive-1.5.dist-info/RECORD
