Metadata-Version: 2.4
Name: hiPhive
Version: 1.5
Summary: High-order force constants for the masses
Author: Fredrik Eriksson, Erik Fransson, Paul Erhart
Maintainer-email: The hiPhive developers team <hiphive@materialsmodeling.org>
License: MIT License
Project-URL: Documentation, https://hiphive.materialsmodeling.org
Project-URL: Repository, https://gitlab.com/materials-modeling/hiphive/
Keywords: chemistry,physics,scientific
Classifier: Development Status :: 5 - Production/Stable
Classifier: Operating System :: OS Independent
Classifier: Programming Language :: Python :: 3 :: Only
Classifier: Programming Language :: Python :: 3
Classifier: Programming Language :: Python :: 3.8
Classifier: Programming Language :: Python :: 3.9
Classifier: Programming Language :: Python :: 3.10
Classifier: Programming Language :: Python :: 3.11
Classifier: Programming Language :: Python :: 3.12
Classifier: Intended Audience :: Science/Research
Requires-Python: >=3.9
License-File: LICENSE
Requires-Dist: ase
Requires-Dist: h5py
Requires-Dist: numba>=0.55
Requires-Dist: numpy>=1.18
Requires-Dist: pandas
Requires-Dist: scipy>=1.0.0
Requires-Dist: spglib>=2.5
Requires-Dist: sympy>=1.1
Requires-Dist: trainstation>=0.2
Dynamic: license-file
